nb_canvas_quiz-0.5.4.dist-info/licenses/LICENSE
nbquiz/__init__.py
nbquiz/question.py
nbquiz/quiz.py
nbquiz/testbank.py
nbquiz/canvas/__init__.py
nbquiz/canvas/export.py
nbquiz/canvas/html.py
nbquiz/cli/__init__.py
nbquiz/cli/export.py
nbquiz/cli/preview.py
nbquiz/cli/send.py
nbquiz/cli/server.py
nbquiz/cli/test.py
nbquiz/resources/__init__.py
nbquiz/resources/canvas_html_template.txt
nbquiz/resources/cell_question_template.md
nbquiz/resources/function_question_template.md
nbquiz/resources/question_template.md
nbquiz/resources/quiz_schema.yaml
nbquiz/resources/test-notebook-template.ipynb
nbquiz/resources/canvas/imsmanifest.xml
nbquiz/resources/canvas/resource_assessment.xml
nbquiz/resources/canvas/resource_file.xml
nbquiz/resources/canvas/assessment/assessment.xml
nbquiz/resources/canvas/assessment/assessment_meta.xml
nbquiz/resources/canvas/assessment/item_essay.xml
nbquiz/resources/canvas/assessment/item_file.xml
nbquiz/resources/canvas/assessment/section.xml
nbquiz/runtime/__init__.py
nbquiz/runtime/checker_pb2.py
nbquiz/runtime/checker_pb2.pyi
nbquiz/runtime/checker_pb2_grpc.py
nbquiz/runtime/client.py
nbquiz/runtime/server.py
nb_canvas_quiz-0.5.4.dist-info/METADATA
nb_canvas_quiz-0.5.4.dist-info/WHEEL
nb_canvas_quiz-0.5.4.dist-info/entry_points.txt
nb_canvas_quiz-0.5.4.dist-info/top_level.txt
nb_canvas_quiz-0.5.4.dist-info/RECORD
