Metadata-Version: 2.4
Name: nb-canvas-quiz
Version: 0.5.4
Summary: quizzes for my CIS-15 class at Cabrillo College
Author-email: Mike Matera <michael.matera@cabrillo.edu>
License-Expression: MIT
Project-URL: Homepage, https://github.com/mike-matera/nb-canvas-quiz
Project-URL: Issues, https://github.com/mike-matera/nb-canvas-quiz/issues
Classifier: Programming Language :: Python :: 3
Classifier: Operating System :: OS Independent
Requires-Python: >=3.10
License-File: LICENSE
Requires-Dist: jinja2
Requires-Dist: jupyterlab
Requires-Dist: ipywidgets
Requires-Dist: grpcio
Requires-Dist: grpcio-tools
Requires-Dist: myst_parser
Requires-Dist: docutils
Requires-Dist: cssutils
Requires-Dist: minify_html
Requires-Dist: pyyaml
Requires-Dist: yamale
Requires-Dist: requests
Requires-Dist: nb-unittest
Dynamic: license-file
